README.rst
setup.py
tramtracker.py
tramtracker.egg-info/PKG-INFO
tramtracker.egg-info/SOURCES.txt
tramtracker.egg-info/dependency_links.txt
tramtracker.egg-info/top_level.txt