Metadata-Version: 1.0
Name: tramtracker
Version: 0.1
Summary: Python command line tool to access Yarra Trams TramTracker data
Home-page: https://github.com/coljac/tramtracker
Author: Colin Jacobs
Author-email: colin@coljac.net
License: Public Domain
Keywords: tramtracker command-line
Platform: UNKNOWN
